[
  {
    "name": "Hektor Kostos",
    "url": "/articles/characters/frihetskämparna/hektor-kostos.html",
    "shorthands": [
      "Hektor"
    ]
  },
  {
    "name": "Odo Orgulas",
    "url": "/articles/characters/frihetskämparna/odo-orgulas.html",
    "shorthands": [
      "Odo",
      "Big B"
    ]
  },
  {
    "name": "Väggmossens Munkkloster",
    "url": "/articles/geografi/farnesh/väggmossens-munkkloster.html",
    "shorthands": []
  },
  {
    "name": "Loxfolk",
    "url": "/articles/folkslag/loxfolk.html",
    "shorthands": []
  },
  {
    "name": "Frihetskämparna",
    "url": "/articles/grupper/frihetskämparna.html",
    "shorthands": []
  }
]